picklenet.py
picklenet-1.0.0.dist-info/LICENSE
picklenet-1.0.0.dist-info/METADATA
picklenet-1.0.0.dist-info/WHEEL
picklenet-1.0.0.dist-info/top_level.txt
picklenet-1.0.0.dist-info/RECORD
